[
    {
        "frame": 2.0,
        "angle": 87.90630546052803,
        "hip": [
            0.3373927175998688,
            0.481903076171875
        ],
        "knee": [
            0.35589835047721863,
            0.6383272409439087
        ],
        "ankle": [
            0.4533505141735077,
            0.623170018196106
        ]
    },
    {
        "frame": 3.0,
        "angle": 90.42320068435149,
        "hip": [
            0.3402048945426941,
            0.4777984619140625
        ],
        "knee": [
            0.36923426389694214,
            0.6303781867027283
        ],
        "ankle": [
            0.4642868936061859,
            0.6130202412605286
        ]
    },
    {
        "frame": 4.0,
        "angle": 98.85268907679418,
        "hip": [
            0.3467741906642914,
            0.4681164622306824
        ],
        "knee": [
            0.3833972215652466,
            0.6163486242294312
        ],
        "ankle": [
            0.47974157333374023,
            0.6078768968582153
        ]
    },
    {
        "frame": 5.0,
        "angle": 105.84096465990905,
        "hip": [
            0.35795992612838745,
            0.4541463553905487
        ],
        "knee": [
            0.39298489689826965,
            0.6050965785980225
        ],
        "ankle": [
            0.491111159324646,
            0.6098576188087463
        ]
    },
    {
        "frame": 6.0,
        "angle": 117.93566634743311,
        "hip": [
            0.3684134781360626,
            0.4459879994392395
        ],
        "knee": [
            0.40297821164131165,
            0.5962762832641602
        ],
        "ankle": [
            0.49761316180229187,
            0.6216043829917908
        ]
    },
    {
        "frame": 7.0,
        "angle": 127.90080720959921,
        "hip": [
            0.37528881430625916,
            0.4465687870979309
        ],
        "knee": [
            0.4085135757923126,
            0.597602903842926
        ],
        "ankle": [
            0.5030878782272339,
            0.6427011489868164
        ]
    },
    {
        "frame": 8.0,
        "angle": 137.12389995918636,
        "hip": [
            0.3896195590496063,
            0.44854065775871277
        ],
        "knee": [
            0.41688674688339233,
            0.6004304885864258
        ],
        "ankle": [
            0.506107747554779,
            0.6675330400466919
        ]
    },
    {
        "frame": 9.0,
        "angle": 146.41164842758246,
        "hip": [
            0.39615577459335327,
            0.45443758368492126
        ],
        "knee": [
            0.4233334958553314,
            0.6036545634269714
        ],
        "ankle": [
            0.5096463561058044,
            0.6933130621910095
        ]
    },
    {
        "frame": 10.0,
        "angle": 153.36827243708444,
        "hip": [
            0.40915852785110474,
            0.46068719029426575
        ],
        "knee": [
            0.4323843717575073,
            0.6043288707733154
        ],
        "ankle": [
            0.5134662389755249,
            0.7166832089424133
        ]
    }
]