[
    {
        "frame": 2,
        "pivot_initiated": false,
        "right_ball_of_foot": [
            0.3899122476577759,
            0.7622124552726746
        ],
        "right_heel": [
            0.4090217053890228,
            0.7438711524009705
        ]
    },
    {
        "frame": 3,
        "pivot_initiated": false,
        "right_ball_of_foot": [
            0.3899303674697876,
            0.7623682618141174
        ],
        "right_heel": [
            0.4089040160179138,
            0.7436952590942383
        ]
    },
    {
        "frame": 4,
        "pivot_initiated": false,
        "right_ball_of_foot": [
            0.3895356059074402,
            0.764892041683197
        ],
        "right_heel": [
            0.40886059403419495,
            0.7449176907539368
        ]
    },
    {
        "frame": 5,
        "pivot_initiated": false,
        "right_ball_of_foot": [
            0.3882482349872589,
            0.766627848148346
        ],
        "right_heel": [
            0.4086644947528839,
            0.7459585666656494
        ]
    },
    {
        "frame": 6,
        "pivot_initiated": false,
        "right_ball_of_foot": [
            0.3849644064903259,
            0.7628931403160095
        ],
        "right_heel": [
            0.40721946954727173,
            0.7459002733230591
        ]
    },
    {
        "frame": 7,
        "pivot_initiated": false,
        "right_ball_of_foot": [
            0.3814859986305237,
            0.7604275941848755
        ],
        "right_heel": [
            0.40408432483673096,
            0.7461913824081421
        ]
    },
    {
        "frame": 8,
        "pivot_initiated": false,
        "right_ball_of_foot": [
            0.37499767541885376,
            0.7606476545333862
        ],
        "right_heel": [
            0.3973669707775116,
            0.7615672945976257
        ]
    },
    {
        "frame": 9,
        "pivot_initiated": false,
        "right_ball_of_foot": [
            0.37300780415534973,
            0.7607111930847168
        ],
        "right_heel": [
            0.39632847905158997,
            0.7651960253715515
        ]
    },
    {
        "frame": 10,
        "pivot_initiated": false,
        "right_ball_of_foot": [
            0.37363526225090027,
            0.760681688785553
        ],
        "right_heel": [
            0.3957470953464508,
            0.7684925198554993
        ]
    },
    {
        "frame": 11,
        "pivot_initiated": false,
        "right_ball_of_foot": [
            0.34338024258613586,
            0.7584521174430847
        ],
        "right_heel": [
            0.36817988753318787,
            0.751311719417572
        ]
    },
    {
        "frame": 12,
        "pivot_initiated": false,
        "right_ball_of_foot": [
            0.3417951762676239,
            0.7506611347198486
        ],
        "right_heel": [
            0.35991141200065613,
            0.7387166619300842
        ]
    },
    {
        "frame": 13,
        "pivot_initiated": false,
        "right_ball_of_foot": [
            0.34652796387672424,
            0.7504583597183228
        ],
        "right_heel": [
            0.3587115406990051,
            0.7343068718910217
        ]
    },
    {
        "frame": 14,
        "pivot_initiated": false,
        "right_ball_of_foot": [
            0.34710487723350525,
            0.7515323758125305
        ],
        "right_heel": [
            0.356304794549942,
            0.7349006533622742
        ]
    },
    {
        "frame": 15,
        "pivot_initiated": false,
        "right_ball_of_foot": [
            0.34022852778434753,
            0.7514688968658447
        ],
        "right_heel": [
            0.3509245216846466,
            0.7322534918785095
        ]
    },
    {
        "frame": 16,
        "pivot_initiated": false,
        "right_ball_of_foot": [
            0.32587817311286926,
            0.748378574848175
        ],
        "right_heel": [
            0.3390848934650421,
            0.7260318994522095
        ]
    }
]