[
    {
        "frame": 1,
        "flat_pivot": false,
        "right_ball_of_foot": [
            0.29972007870674133,
            0.8194275498390198
        ],
        "right_heel": [
            0.3266217112541199,
            0.7917702198028564
        ]
    },
    {
        "frame": 2,
        "flat_pivot": true,
        "right_ball_of_foot": [
            0.254624605178833,
            0.7133316397666931
        ],
        "right_heel": [
            0.24672459065914154,
            0.7039196491241455
        ]
    },
    {
        "frame": 3,
        "flat_pivot": false,
        "right_ball_of_foot": [
            0.23025499284267426,
            0.6990103125572205
        ],
        "right_heel": [
            0.2261507362127304,
            0.6658626794815063
        ]
    },
    {
        "frame": 4,
        "flat_pivot": false,
        "right_ball_of_foot": [
            0.20493683218955994,
            0.6973096132278442
        ],
        "right_heel": [
            0.23070600628852844,
            0.6668129563331604
        ]
    },
    {
        "frame": 5,
        "flat_pivot": false,
        "right_ball_of_foot": [
            0.1955277919769287,
            0.715669572353363
        ],
        "right_heel": [
            0.2082698941230774,
            0.67557692527771
        ]
    },
    {
        "frame": 6,
        "flat_pivot": false,
        "right_ball_of_foot": [
            0.2593976855278015,
            0.7464180588722229
        ],
        "right_heel": [
            0.22924697399139404,
            0.7078985571861267
        ]
    },
    {
        "frame": 7,
        "flat_pivot": false,
        "right_ball_of_foot": [
            0.25250354409217834,
            0.7484099268913269
        ],
        "right_heel": [
            0.2307201474905014,
            0.7127014994621277
        ]
    },
    {
        "frame": 8,
        "flat_pivot": false,
        "right_ball_of_foot": [
            0.2681403160095215,
            0.7534118294715881
        ],
        "right_heel": [
            0.23722568154335022,
            0.7191324234008789
        ]
    },
    {
        "frame": 9,
        "flat_pivot": false,
        "right_ball_of_foot": [
            0.2739127576351166,
            0.7477375864982605
        ],
        "right_heel": [
            0.2559967339038849,
            0.717932403087616
        ]
    },
    {
        "frame": 10,
        "flat_pivot": false,
        "right_ball_of_foot": [
            0.33863937854766846,
            0.7405970692634583
        ],
        "right_heel": [
            0.291559100151062,
            0.7201621532440186
        ]
    },
    {
        "frame": 11,
        "flat_pivot": true,
        "right_ball_of_foot": [
            0.3877076506614685,
            0.7297566533088684
        ],
        "right_heel": [
            0.3304237127304077,
            0.7218977808952332
        ]
    },
    {
        "frame": 12,
        "flat_pivot": false,
        "right_ball_of_foot": [
            0.3941229283809662,
            0.735512375831604
        ],
        "right_heel": [
            0.3529300391674042,
            0.7237792015075684
        ]
    },
    {
        "frame": 13,
        "flat_pivot": false,
        "right_ball_of_foot": [
            0.39459964632987976,
            0.7358404994010925
        ],
        "right_heel": [
            0.37078750133514404,
            0.7244452238082886
        ]
    },
    {
        "frame": 14,
        "flat_pivot": true,
        "right_ball_of_foot": [
            0.399990975856781,
            0.7393282055854797
        ],
        "right_heel": [
            0.3915489614009857,
            0.7338151931762695
        ]
    },
    {
        "frame": 15,
        "flat_pivot": true,
        "right_ball_of_foot": [
            0.38076385855674744,
            0.7408138513565063
        ],
        "right_heel": [
            0.402993768453598,
            0.7390956282615662
        ]
    },
    {
        "frame": 16,
        "flat_pivot": true,
        "right_ball_of_foot": [
            0.38443711400032043,
            0.7492844462394714
        ],
        "right_heel": [
            0.39783430099487305,
            0.7471834421157837
        ]
    },
    {
        "frame": 17,
        "flat_pivot": true,
        "right_ball_of_foot": [
            0.3649370074272156,
            0.7612156867980957
        ],
        "right_heel": [
            0.3828824460506439,
            0.7652672529220581
        ]
    },
    {
        "frame": 18,
        "flat_pivot": true,
        "right_ball_of_foot": [
            0.33951932191848755,
            0.7720672488212585
        ],
        "right_heel": [
            0.3641890585422516,
            0.769500195980072
        ]
    },
    {
        "frame": 19,
        "flat_pivot": true,
        "right_ball_of_foot": [
            0.3202206492424011,
            0.7704600095748901
        ],
        "right_heel": [
            0.3557024598121643,
            0.7628553509712219
        ]
    },
    {
        "frame": 20,
        "flat_pivot": true,
        "right_ball_of_foot": [
            0.31021302938461304,
            0.7674198746681213
        ],
        "right_heel": [
            0.35192298889160156,
            0.7677029967308044
        ]
    },
    {
        "frame": 21,
        "flat_pivot": true,
        "right_ball_of_foot": [
            0.28770342469215393,
            0.7650225758552551
        ],
        "right_heel": [
            0.3290126919746399,
            0.7637535929679871
        ]
    },
    {
        "frame": 22,
        "flat_pivot": true,
        "right_ball_of_foot": [
            0.2726466655731201,
            0.7634778022766113
        ],
        "right_heel": [
            0.3179905116558075,
            0.7623606324195862
        ]
    },
    {
        "frame": 23,
        "flat_pivot": true,
        "right_ball_of_foot": [
            0.25721752643585205,
            0.7616140842437744
        ],
        "right_heel": [
            0.3023582994937897,
            0.7652485966682434
        ]
    },
    {
        "frame": 24,
        "flat_pivot": true,
        "right_ball_of_foot": [
            0.24258513748645782,
            0.7617865204811096
        ],
        "right_heel": [
            0.29406335949897766,
            0.7662497162818909
        ]
    }
]