[
    {
        "frame": 2,
        "left_takeoff_flat_com_above": false,
        "right_takeoff_flat_com_above": false,
        "left_foot": [
            0.29076850414276123,
            0.569826066493988
        ],
        "right_foot": [
            0.29188892245292664,
            0.5713163614273071
        ],
        "left_hip": [
            0.3188845217227936,
            0.4452371895313263
        ],
        "right_hip": [
            0.3097669184207916,
            0.4478008449077606
        ],
        "left_shoulder": [
            0.316932737827301,
            0.3569936156272888
        ],
        "right_shoulder": [
            0.29886505007743835,
            0.35361695289611816
        ]
    },
    {
        "frame": 3,
        "left_takeoff_flat_com_above": false,
        "right_takeoff_flat_com_above": false,
        "left_foot": [
            0.3099783957004547,
            0.5318835377693176
        ],
        "right_foot": [
            0.3126920461654663,
            0.5600283741950989
        ],
        "left_hip": [
            0.3214515149593353,
            0.4257780611515045
        ],
        "right_hip": [
            0.3224245309829712,
            0.430005818605423
        ],
        "left_shoulder": [
            0.3159153163433075,
            0.34224942326545715
        ],
        "right_shoulder": [
            0.31237369775772095,
            0.34562602639198303
        ]
    }
]