[
    {
        "keypoints": [
            {
                "x": 108.68336588944042,
                "y": 44.84480244262264,
                "z": -14.769501294746608,
                "visibility": 0.9974933862686157
            },
            {
                "x": 108.55379561381193,
                "y": 43.853238781593824,
                "z": -15.593194578058323,
                "visibility": 0.9977779984474182
            },
            {
                "x": 108.61525523480684,
                "y": 43.748158925378945,
                "z": -15.613226307327508,
                "visibility": 0.997307538986206
            },
            {
                "x": 108.6678992298523,
                "y": 43.66096470691146,
                "z": -15.608731771904434,
                "visibility": 0.9978944659233093
            },
            {
                "x": 108.5714546168943,
                "y": 44.09007200653694,
                "z": -14.273727558327378,
                "visibility": 0.9982184767723083
            },
            {
                "x": 108.55232480108795,
                "y": 44.025592131740886,
                "z": -14.293460962374246,
                "visibility": 0.9984703660011292
            },
            {
                "x": 108.53819019830645,
                "y": 43.97882676239414,
                "z": -14.303365822274952,
                "visibility": 0.9989019632339478
            },
            {
                "x": 108.95624327651578,
                "y": 43.29872850905783,
                "z": -16.267284700173057,
                "visibility": 0.9975302815437317
            },
            {
                "x": 108.66900927719115,
                "y": 43.53590399859709,
                "z": -10.348853397666064,
                "visibility": 0.9952945113182068
            },
            {
                "x": 109.20463486937479,
                "y": 44.83288330932162,
                "z": -14.57532048249989,
                "visibility": 0.9961656332015991
            },
            {
                "x": 109.06847831286906,
                "y": 44.92483685575448,
                "z": -12.994299714849268,
                "visibility": 0.9965498447418213
            },
            {
                "x": 110.35176703974764,
                "y": 44.856638322373236,
                "z": -17.294552571336595,
                "visibility": 0.9997828602790833
            },
            {
                "x": 110.03813241454712,
                "y": 45.806182066428946,
                "z": -3.42525428365783,
                "visibility": 0.9997166991233826
            },
            {
                "x": 112.73499242430854,
                "y": 50.58692006984132,
                "z": -17.819563335842375,
                "visibility": 0.3305540382862091
            },
            {
                "x": 111.599728510067,
                "y": 50.56980684003389,
                "z": -3.048679107119435,
                "visibility": 0.12075860798358917
            },
            {
                "x": 114.94537418781438,
                "y": 55.4093496012224,
                "z": -17.19852885132792,
                "visibility": 0.3393465280532837
            },
            {
                "x": 111.77444996120363,
                "y": 57.30861747202638,
                "z": -11.731286696394555,
                "visibility": 0.6970973610877991
            },
            {
                "x": 115.48178606352971,
                "y": 56.522722456902166,
                "z": -18.64319764788921,
                "visibility": 0.2931859493255615
            },
            {
                "x": 111.83821293042668,
                "y": 59.3682686825067,
                "z": -13.38687605033244,
                "visibility": 0.6639505624771118
            },
            {
                "x": 115.45464540609457,
                "y": 56.16713729268721,
                "z": -19.28086781059552,
                "visibility": 0.2851565182209015
            },
            {
                "x": 111.74801233374977,
                "y": 59.53058535463157,
                "z": -15.542538261529014,
                "visibility": 0.6717867851257324
            },
            {
                "x": 115.22790898673783,
                "y": 55.73836300726339,
                "z": -17.283198868398813,
                "visibility": 0.19895905256271362
            },
            {
                "x": 111.63444524058986,
                "y": 59.48789015886065,
                "z": -12.98846271592576,
                "visibility": 0.5846990942955017
            },
            {
                "x": 117.97730198681083,
                "y": 51.4712716587252,
                "z": -3.65844285317169,
                "visibility": 0.9985604882240295
            },
            {
                "x": 117.8188427291885,
                "y": 51.13638887737999,
                "z": 3.633113827682552,
                "visibility": 0.9990689158439636
            },
            {
                "x": 115.73821624920096,
                "y": 52.56780879643225,
                "z": 2.753872214530191,
                "visibility": 0.47738394141197205
            },
            {
                "x": 114.42660281439245,
                "y": 54.041156128512725,
                "z": 7.649976223756057,
                "visibility": 0.24437935650348663
            },
            {
                "x": 114.3386963155492,
                "y": 57.92946694865101,
                "z": 16.397904895576215,
                "visibility": 0.345901221036911
            },
            {
                "x": 112.14145011221987,
                "y": 57.64739929464933,
                "z": 11.564450050261767,
                "visibility": 0.3279196619987488
            },
            {
                "x": 114.46829434236115,
                "y": 58.98057077381796,
                "z": 17.544365256049204,
                "visibility": 0.3130747079849243
            },
            {
                "x": 112.43368857496387,
                "y": 58.805322050195365,
                "z": 11.845196054150618,
                "visibility": 0.3366665840148926
            },
            {
                "x": 113.35956980991286,
                "y": 59.047983023667506,
                "z": 14.202960884175715,
                "visibility": 0.2997732162475586
            },
            {
                "x": 110.45405790202364,
                "y": 57.31626754827002,
                "z": 7.70962854892738,
                "visibility": 0.31123918294906616
            }
        ],
        "gaze_features": {
            "gaze_vector": [
                -0.18172192062506573,
                -0.9833499598639017
            ],
            "gaze_angle_degrees": -100.47007289970699
        },
        "shoulder_width": 0.006443470582425467
    },
    {
        "keypoints": [
            {
                "x": 23.095512706908494,
                "y": 9.25029592569141,
                "z": -5.504722283650026,
                "visibility": 0.9992043375968933
            },
            {
                "x": 23.05733026276296,
                "y": 9.087961051506403,
                "z": -5.91253293595591,
                "visibility": 0.9994933605194092
            },
            {
                "x": 23.074924406245685,
                "y": 9.08112505357372,
                "z": -5.916062472234423,
                "visibility": 0.9992608428001404
            },
            {
                "x": 23.091071043277108,
                "y": 9.078362894002952,
                "z": -5.914810280009771,
                "visibility": 0.9995344877243042
            },
            {
                "x": 23.04274812243027,
                "y": 9.035373935284882,
                "z": -5.585595757959783,
                "visibility": 0.9996525049209595
            },
            {
                "x": 23.049327336684264,
                "y": 8.996377516621186,
                "z": -5.589461393338975,
                "visibility": 0.9996071457862854
            },
            {
                "x": 23.055178831941507,
                "y": 8.960313785685535,
                "z": -5.591992051021813,
                "visibility": 0.9997848868370056
            },
            {
                "x": 23.203740583098117,
                "y": 8.97916210427846,
                "z": -6.467930255449323,
                "visibility": 0.9994246959686279
            },
            {
                "x": 23.156553855671273,
                "y": 8.851747827509685,
                "z": -4.982005396623043,
                "visibility": 0.9994283318519592
            },
            {
                "x": 23.21451954894643,
                "y": 9.285926396134446,
                "z": -5.537331332236666,
                "visibility": 0.9988459348678589
            },
            {
                "x": 23.202729311467756,
                "y": 9.241015029875916,
                "z": -5.126221158376037,
                "visibility": 0.9991525411605835
            },
            {
                "x": 23.668289026802487,
                "y": 9.79270237050579,
                "z": -6.03255204106698,
                "visibility": 0.999675989151001
            },
            {
                "x": 23.584934466948635,
                "y": 8.796182417192476,
                "z": -2.9720517241179403,
                "visibility": 0.9998038411140442
            },
            {
                "x": 23.699987435200413,
                "y": 11.211512502130478,
                "z": -5.0473385011582055,
                "visibility": 0.15985892713069916
            },
            {
                "x": 23.85195974950255,
                "y": 9.410305866569363,
                "z": -0.3498267102871549,
                "visibility": 0.006550082005560398
            },
            {
                "x": 24.015254340293627,
                "y": 11.32271074087359,
                "z": -3.765062184806177,
                "visibility": 0.049983590841293335
            },
            {
                "x": 23.798515035280772,
                "y": 10.124774230632934,
                "z": 0.7829292846579071,
                "visibility": 0.030039111152291298
            },
            {
                "x": 23.98963744187671,
                "y": 11.296193612417097,
                "z": -4.181102060004119,
                "visibility": 0.052584487944841385
            },
            {
                "x": 23.773845956156624,
                "y": 10.17359088998165,
                "z": 0.6143748420854888,
                "visibility": 0.038006436079740524
            },
            {
                "x": 23.998370069837705,
                "y": 11.121281295190176,
                "z": -4.356748044884441,
                "visibility": 0.04885999113321304
            },
            {
                "x": 23.76779617234441,
                "y": 10.33996886780255,
                "z": 0.20347178681704628,
                "visibility": 0.0340464785695076
            },
            {
                "x": 24.027714793088105,
                "y": 11.098750758131409,
                "z": -3.810437298422649,
                "visibility": 0.02608569525182247
            },
            {
                "x": 23.77990962016769,
                "y": 10.383076799653605,
                "z": 0.5961834162960841,
                "visibility": 0.025666533038020134
            },
            {
                "x": 24.648942921389665,
                "y": 11.822314618211575,
                "z": -0.9755324110381018,
                "visibility": 0.9999507665634155
            },
            {
                "x": 24.69537615230761,
                "y": 11.37722621329222,
                "z": 0.9740606762039907,
                "visibility": 0.9999706745147705
            },
            {
                "x": 24.438531004165988,
                "y": 11.474903155471747,
                "z": 4.48459954791693,
                "visibility": 0.008619679138064384
            },
            {
                "x": 23.885296021364553,
                "y": 11.554892758547712,
                "z": 5.871083687867203,
                "visibility": 0.008702202700078487
            },
            {
                "x": 24.736225577517523,
                "y": 12.3538845934967,
                "z": 10.233647536068991,
                "visibility": 0.03835294023156166
            },
            {
                "x": 23.87132064401008,
                "y": 12.786620612884033,
                "z": 11.161179926778997,
                "visibility": 0.03545597940683365
            },
            {
                "x": 24.80521214867806,
                "y": 12.415669324340627,
                "z": 10.79683759577283,
                "visibility": 0.02526211366057396
            },
            {
                "x": 24.214258716949725,
                "y": 12.935758392292836,
                "z": 11.710440215496007,
                "visibility": 0.04341501370072365
            },
            {
                "x": 24.66440546290643,
                "y": 12.791514374420759,
                "z": 10.239199615608225,
                "visibility": 0.0471484549343586
            },
            {
                "x": 23.751564271234347,
                "y": 13.424344366073765,
                "z": 11.2825860603321,
                "visibility": 0.060955826193094254
            }
        ],
        "gaze_features": {
            "gaze_vector": [
                -0.2701442585459097,
                -0.9628198583196551
            ],
            "gaze_angle_degrees": -105.67285125277893
        },
        "shoulder_width": 0.030059548713546536
    },
    {
        "keypoints": [
            {
                "x": 30.50777411154864,
                "y": 12.177745917116269,
                "z": -9.981610932676897,
                "visibility": 0.9999896287918091
            },
            {
                "x": 30.521730391692117,
                "y": 11.904138701445794,
                "z": -10.08801974866623,
                "visibility": 0.9999874830245972
            },
            {
                "x": 30.570851075857913,
                "y": 11.865227163933326,
                "z": -10.09294120120842,
                "visibility": 0.999983549118042
            },
            {
                "x": 30.62030020442006,
                "y": 11.833319833508181,
                "z": -10.09230516602818,
                "visibility": 0.9999887943267822
            },
            {
                "x": 30.42836616197622,
                "y": 11.941276378547794,
                "z": -9.74632092656358,
                "visibility": 0.99998939037323
            },
            {
                "x": 30.40512741758341,
                "y": 11.931286194825367,
                "z": -9.751497835858489,
                "visibility": 0.9999899864196777
            },
            {
                "x": 30.377290451641652,
                "y": 11.922856121985621,
                "z": -9.75495236709871,
                "visibility": 0.9999932050704956
            },
            {
                "x": 30.769408746961552,
                "y": 11.65672362303375,
                "z": -9.151546573614901,
                "visibility": 0.9999891519546509
            },
            {
                "x": 30.454375830125567,
                "y": 11.7647466389631,
                "z": -7.637432894958013,
                "visibility": 0.999975323677063
            },
            {
                "x": 30.69146055026182,
                "y": 12.202521312077733,
                "z": -9.499352245793407,
                "visibility": 0.9999891519546509
            },
            {
                "x": 30.571023118160763,
                "y": 12.287577983927124,
                "z": -9.08483651900866,
                "visibility": 0.9999874830245972
            },
            {
                "x": 31.449606665003962,
                "y": 12.015344499977905,
                "z": -7.817694127823503,
                "visibility": 0.9999902248382568
            },
            {
                "x": 30.45005913234492,
                "y": 12.045423229259859,
                "z": -4.2858165131252255,
                "visibility": 0.9999970197677612
            },
            {
                "x": 32.34286594162075,
                "y": 12.559870118661406,
                "z": -6.356645724465605,
                "visibility": 0.935735821723938
            },
            {
                "x": 30.379487901055352,
                "y": 13.449799334037381,
                "z": -2.7839282647770607,
                "visibility": 0.8319597840309143
            },
            {
                "x": 32.46538091486382,
                "y": 14.306048661928527,
                "z": -5.192842106509421,
                "visibility": 0.889969527721405
            },
            {
                "x": 30.215977332403902,
                "y": 14.989547967494603,
                "z": -4.113899983623445,
                "visibility": 0.9844373464584351
            },
            {
                "x": 32.59083624746472,
                "y": 14.919713129395273,
                "z": -5.511295667465367,
                "visibility": 0.7751631140708923
            },
            {
                "x": 30.038799827481956,
                "y": 15.26283586222418,
                "z": -4.470691933586713,
                "visibility": 0.9738070964813232
            },
            {
                "x": 32.47654802433985,
                "y": 14.964893784155604,
                "z": -5.784698908738902,
                "visibility": 0.7747448086738586
            },
            {
                "x": 30.025476975817163,
                "y": 15.32589979302566,
                "z": -4.993278574441946,
                "visibility": 0.9749667644500732
            },
            {
                "x": 32.42198715402174,
                "y": 14.721820167189016,
                "z": -5.234934145760785,
                "visibility": 0.6492400765419006
            },
            {
                "x": 30.121447907091422,
                "y": 15.242695182633486,
                "z": -4.373340427999607,
                "visibility": 0.9603356719017029
            },
            {
                "x": 32.27885056475046,
                "y": 13.443461139198222,
                "z": -1.1792377349644056,
                "visibility": 0.9999675750732422
            },
            {
                "x": 31.86601941884781,
                "y": 14.066737818661434,
                "z": 1.1768310977506466,
                "visibility": 0.9999831914901733
            },
            {
                "x": 32.13939724478115,
                "y": 15.971596712592355,
                "z": -1.0582737491485612,
                "visibility": 0.5654636025428772
            },
            {
                "x": 31.183684005527542,
                "y": 15.626913868880768,
                "z": 0.19948512737216492,
                "visibility": 0.7599745392799377
            },
            {
                "x": 32.75580135558574,
                "y": 16.025168339669058,
                "z": 4.6284133439147315,
                "visibility": 0.21354371309280396
            },
            {
                "x": 31.77043167270263,
                "y": 16.775043390366516,
                "z": 4.05391587071317,
                "visibility": 0.6554104685783386
            },
            {
                "x": 32.8832247478632,
                "y": 15.891093948365425,
                "z": 5.153005515781429,
                "visibility": 0.1001802533864975
            },
            {
                "x": 31.986725341209375,
                "y": 16.94351190538197,
                "z": 4.422007546094248,
                "visibility": 0.5268911719322205
            },
            {
                "x": 32.81445214064891,
                "y": 16.797006154346505,
                "z": 4.469377504325909,
                "visibility": 0.29522591829299927
            },
            {
                "x": 31.549693578038877,
                "y": 17.82073996741482,
                "z": 3.6058642767046907,
                "visibility": 0.715495228767395
            }
        ],
        "gaze_features": {
            "gaze_vector": [
                -0.12486287124085806,
                -0.9921740086222219
            ],
            "gaze_angle_degrees": -97.1728368403895
        },
        "shoulder_width": 0.022865925937765416
    },
    {
        "keypoints": [
            {
                "x": 26.07556638737673,
                "y": 10.198876903949282,
                "z": -8.660855335296382,
                "visibility": 0.9999587535858154
            },
            {
                "x": 26.111154218605403,
                "y": 9.98390919874679,
                "z": -8.724428253469618,
                "visibility": 0.9999737739562988
            },
            {
                "x": 26.15654512296132,
                "y": 9.947116162272382,
                "z": -8.729083773366106,
                "visibility": 0.9999620914459229
            },
            {
                "x": 26.201989100575762,
                "y": 9.913332821833654,
                "z": -8.72857183755989,
                "visibility": 0.9999794960021973
            },
            {
                "x": 26.02056037768419,
                "y": 10.027105302724003,
                "z": -8.418406739105343,
                "visibility": 0.999976396560669
            },
            {
                "x": 25.998700829328047,
                "y": 10.02477560781321,
                "z": -8.423805284621219,
                "visibility": 0.9999738931655884
            },
            {
                "x": 25.97353083647123,
                "y": 10.02462081080917,
                "z": -8.426620378708966,
                "visibility": 0.9999823570251465
            },
            {
                "x": 26.330795687637,
                "y": 9.868971317554601,
                "z": -7.757896768412034,
                "visibility": 0.9999692440032959
            },
            {
                "x": 26.032216592088364,
                "y": 9.946883966766322,
                "z": -6.424141456364512,
                "visibility": 0.9998408555984497
            },
            {
                "x": 26.181438692596636,
                "y": 10.266267779657863,
                "z": -8.181660201127386,
                "visibility": 0.9999270439147949
            },
            {
                "x": 26.090225663659268,
                "y": 10.318144678483032,
                "z": -7.822350370968966,
                "visibility": 0.9999159574508667
            },
            {
                "x": 26.90664275404958,
                "y": 10.219263669381279,
                "z": -6.604549071875863,
                "visibility": 0.9999368190765381
            },
            {
                "x": 25.90981860099436,
                "y": 10.298897882416496,
                "z": -3.4909765066335834,
                "visibility": 0.9999476671218872
            },
            {
                "x": 27.666815458715043,
                "y": 9.827566436052702,
                "z": -4.648247201529268,
                "visibility": 0.2371138483285904
            },
            {
                "x": 25.50734860187752,
                "y": 12.043796248578609,
                "z": -2.9587559351540884,
                "visibility": 0.06374040246009827
            },
            {
                "x": 28.28389160146065,
                "y": 10.509052506486245,
                "z": -2.9455263197731445,
                "visibility": 0.1142713651061058
            },
            {
                "x": 25.395624969904926,
                "y": 12.034929697325806,
                "z": -5.100401510478344,
                "visibility": 0.1362619251012802
            },
            {
                "x": 28.4692300543971,
                "y": 10.717243419990465,
                "z": -3.1127551817763073,
                "visibility": 0.08147981017827988
            },
            {
                "x": 25.346145213256595,
                "y": 12.160380506478045,
                "z": -5.555730263703114,
                "visibility": 0.1376720815896988
            },
            {
                "x": 28.383114269664173,
                "y": 10.759456562992028,
                "z": -3.4990013491769223,
                "visibility": 0.08964340388774872
            },
            {
                "x": 25.4486540007173,
                "y": 12.130861823500606,
                "z": -5.966157934520465,
                "visibility": 0.14462390542030334
            },
            {
                "x": 28.309028423530886,
                "y": 10.674890959685268,
                "z": -3.026403884458664,
                "visibility": 0.06993058323860168
            },
            {
                "x": 25.504453897901985,
                "y": 12.089347478402994,
                "z": -5.346015152555547,
                "visibility": 0.11890970915555954
            },
            {
                "x": 28.25525636709912,
                "y": 11.54582534351251,
                "z": -1.1812700354094534,
                "visibility": 0.9994693398475647
            },
            {
                "x": 27.909486299176166,
                "y": 11.84497497659032,
                "z": 1.1759860673188884,
                "visibility": 0.9995712637901306
            },
            {
                "x": 27.429790286129812,
                "y": 12.350944463993715,
                "z": -2.273645818075083,
                "visibility": 0.31414079666137695
            },
            {
                "x": 26.927960512891588,
                "y": 12.864789801824061,
                "z": 2.685548621413964,
                "visibility": 0.020624855533242226
            },
            {
                "x": 27.32397326555421,
                "y": 14.048086848716768,
                "z": 0.3869343921163422,
                "visibility": 0.3916071653366089
            },
            {
                "x": 27.70931165909542,
                "y": 12.495443044493012,
                "z": 6.2959999435742,
                "visibility": 0.04711861163377762
            },
            {
                "x": 27.568346873059767,
                "y": 14.1589391946952,
                "z": 0.6053267737157902,
                "visibility": 0.4409550130367279
            },
            {
                "x": 27.529716175008833,
                "y": 12.660741919563668,
                "z": 6.6352165697618535,
                "visibility": 0.08231179416179657
            },
            {
                "x": 27.270950868899146,
                "y": 15.101885144801601,
                "z": -0.9879609879868825,
                "visibility": 0.5178657174110413
            },
            {
                "x": 27.664836268449108,
                "y": 12.677340581168243,
                "z": 5.531894289313251,
                "visibility": 0.07669540494680405
            }
        ],
        "gaze_features": {
            "gaze_vector": [
                0.017168090279688162,
                -0.9998526174772703
            ],
            "gaze_angle_degrees": -89.01629255710459
        },
        "shoulder_width": 0.02695352639521127
    },
    {
        "keypoints": [
            {
                "x": 26.582466463070944,
                "y": 10.127235389886772,
                "z": -10.487170452754327,
                "visibility": 0.9999759197235107
            },
            {
                "x": 26.65999484165174,
                "y": 9.90084300403218,
                "z": -10.654252326675923,
                "visibility": 0.9999830722808838
            },
            {
                "x": 26.70481930358433,
                "y": 9.88920296943525,
                "z": -10.65990618607312,
                "visibility": 0.9999759197235107
            },
            {
                "x": 26.749495570632003,
                "y": 9.876898303233247,
                "z": -10.659665930729396,
                "visibility": 0.9999898672103882
            },
            {
                "x": 26.549495346554483,
                "y": 9.889024461960238,
                "z": -10.290611268996981,
                "visibility": 0.9999839067459106
            },
            {
                "x": 26.517530158953804,
                "y": 9.873179958848116,
                "z": -10.296251656131915,
                "visibility": 0.9999768733978271
            },
            {
                "x": 26.4829603339819,
                "y": 9.856024155542203,
                "z": -10.299959896320347,
                "visibility": 0.9999849796295166
            },
            {
                "x": 26.86565566125759,
                "y": 9.829701600453502,
                "z": -9.83051554963201,
                "visibility": 0.9999814033508301
            },
            {
                "x": 26.5437965796164,
                "y": 9.785238644225023,
                "z": -8.141045024654453,
                "visibility": 0.9998064637184143
            },
            {
                "x": 26.69398985010034,
                "y": 10.231592656079728,
                "z": -10.004594018423212,
                "visibility": 0.9999734163284302
            },
            {
                "x": 26.556173097883818,
                "y": 10.233442846764117,
                "z": -9.545430130531567,
                "visibility": 0.9999587535858154
            },
            {
                "x": 27.39329232211093,
                "y": 10.186866990737082,
                "z": -8.169638778623323,
                "visibility": 0.999988317489624
            },
            {
                "x": 26.396666003420698,
                "y": 10.26894001245526,
                "z": -4.414918443360663,
                "visibility": 0.9999842643737793
            },
            {
                "x": 28.22674035487084,
                "y": 10.281611797803984,
                "z": -5.310166269179152,
                "visibility": 0.41110050678253174
            },
            {
                "x": 26.252984326364828,
                "y": 11.351640614756368,
                "z": -1.7887101558786733,
                "visibility": 0.147674098610878
            },
            {
                "x": 28.632823529438518,
                "y": 11.428617753272823,
                "z": -2.2071245201646863,
                "visibility": 0.18574006855487823
            },
            {
                "x": 26.399297585316454,
                "y": 12.643362243409914,
                "z": -1.4251257939700965,
                "visibility": 0.3001006543636322
            },
            {
                "x": 28.845777333683806,
                "y": 11.809499938585356,
                "z": -2.1793489254562823,
                "visibility": 0.10751381516456604
            },
            {
                "x": 26.443199197283892,
                "y": 12.862517779051174,
                "z": -1.3996379577975624,
                "visibility": 0.21332032978534698
            },
            {
                "x": 28.744611870959126,
                "y": 11.80834244671909,
                "z": -2.4968685352875015,
                "visibility": 0.10742375999689102
            },
            {
                "x": 26.42686183391058,
                "y": 12.999049052909916,
                "z": -1.9534206309695057,
                "visibility": 0.21673265099525452
            },
            {
                "x": 28.64656748232583,
                "y": 11.714276866208047,
                "z": -2.210322077411637,
                "visibility": 0.062066592276096344
            },
            {
                "x": 26.502016848955694,
                "y": 12.902167769585494,
                "z": -1.6443252547997833,
                "visibility": 0.162042036652565
            },
            {
                "x": 28.47157402238913,
                "y": 12.202363455805532,
                "z": -1.5472323446889502,
                "visibility": 0.9997832179069519
            },
            {
                "x": 28.025150403846055,
                "y": 12.533187205295537,
                "z": 1.5422845160360759,
                "visibility": 0.9997342228889465
            },
            {
                "x": 27.47726493280847,
                "y": 12.81914719875468,
                "z": -4.970805034822986,
                "visibility": 0.2179575264453888
            },
            {
                "x": 27.51337508643267,
                "y": 13.107614155683628,
                "z": 5.540507150565901,
                "visibility": 0.007542524486780167
            },
            {
                "x": 27.289140507917516,
                "y": 15.104548088727999,
                "z": -2.2285740457232968,
                "visibility": 0.4713747799396515
            },
            {
                "x": 28.196917256970295,
                "y": 13.967644084580842,
                "z": 12.100175223837237,
                "visibility": 0.02112344093620777
            },
            {
                "x": 27.3632514226371,
                "y": 15.417088855635921,
                "z": -2.029217402841058,
                "visibility": 0.29607319831848145
            },
            {
                "x": 28.410418933214356,
                "y": 13.85179048792178,
                "z": 12.726127963946215,
                "visibility": 0.05192527920007706
            },
            {
                "x": 27.14088499782269,
                "y": 15.785931329237663,
                "z": -3.9549860751756536,
                "visibility": 0.7251900434494019
            },
            {
                "x": 28.199313074276414,
                "y": 14.9211703909084,
                "z": 11.864598123183503,
                "visibility": 0.059853311628103256
            }
        ],
        "gaze_features": {
            "gaze_vector": [
                0.2031065792562193,
                -0.9791566358161686
            ],
            "gaze_angle_degrees": -78.28131759420693
        },
        "shoulder_width": 0.026545494855924483
    },
    {
        "keypoints": [
            {
                "x": 24.715938874331343,
                "y": 9.179425107305606,
                "z": -8.842789763587744,
                "visibility": 0.9999854564666748
            },
            {
                "x": 24.75172279271231,
                "y": 8.957806274716198,
                "z": -8.879861065307297,
                "visibility": 0.999988317489624
            },
            {
                "x": 24.779568873793487,
                "y": 8.920817102715215,
                "z": -8.885339117535919,
                "visibility": 0.9999903440475464
            },
            {
                "x": 24.805940726426325,
                "y": 8.888386130094869,
                "z": -8.88383717030757,
                "visibility": 0.9999908208847046
            },
            {
                "x": 24.68239299078141,
                "y": 9.020857259662423,
                "z": -8.673375659985902,
                "visibility": 0.9999881982803345
            },
            {
                "x": 24.662024820576036,
                "y": 9.027752049536376,
                "z": -8.679586719952761,
                "visibility": 0.999991774559021
            },
            {
                "x": 24.638213361919618,
                "y": 9.036700082374583,
                "z": -8.683366740249948,
                "visibility": 0.9999922513961792
            },
            {
                "x": 24.855165173251283,
                "y": 8.815042238168854,
                "z": -7.771242298782889,
                "visibility": 0.9999932050704956
            },
            {
                "x": 24.646095761659378,
                "y": 8.986537303514964,
                "z": -6.846388264248215,
                "visibility": 0.9999654293060303
            },
            {
                "x": 24.807119287887808,
                "y": 9.258767548551681,
                "z": -8.274710306385789,
                "visibility": 0.9999834299087524
            },
            {
                "x": 24.73138336790844,
                "y": 9.320953091588471,
                "z": -8.040542052798878,
                "visibility": 0.9999804496765137
            },
            {
                "x": 25.321195888576252,
                "y": 9.077003188519868,
                "z": -6.243648525877478,
                "visibility": 0.9999942779541016
            },
            {
                "x": 24.36343812222871,
                "y": 9.364579371471399,
                "z": -3.9153282385643413,
                "visibility": 0.9999939203262329
            },
            {
                "x": 25.794417060762026,
                "y": 10.319303471339257,
                "z": -4.775920644769996,
                "visibility": 0.9255102276802063
            },
            {
                "x": 24.265929613856425,
                "y": 10.808254537874161,
                "z": -1.7387308001623174,
                "visibility": 0.8690108060836792
            },
            {
                "x": 25.76282175802813,
                "y": 11.64242966344639,
                "z": -4.220268697264542,
                "visibility": 0.8880584239959717
            },
            {
                "x": 24.647871816823454,
                "y": 11.368545531201969,
                "z": -2.104561718899608,
                "visibility": 0.9327863454818726
            },
            {
                "x": 25.867058743594267,
                "y": 11.984161156201523,
                "z": -4.58625745905471,
                "visibility": 0.8252553343772888
            },
            {
                "x": 24.788804360646687,
                "y": 11.755041827063707,
                "z": -2.4214815670193617,
                "visibility": 0.912347674369812
            },
            {
                "x": 25.77824161268966,
                "y": 11.941283283379068,
                "z": -4.896369010160377,
                "visibility": 0.8375383019447327
            },
            {
                "x": 24.734572054231922,
                "y": 11.60082480126177,
                "z": -2.8612315423680275,
                "visibility": 0.916304349899292
            },
            {
                "x": 25.717892695484387,
                "y": 11.817700642603757,
                "z": -4.290048159404616,
                "visibility": 0.7907615900039673
            },
            {
                "x": 24.733299043594087,
                "y": 11.48198104524795,
                "z": -2.2930691854813916,
                "visibility": 0.8846238851547241
            },
            {
                "x": 25.9146590752345,
                "y": 11.85839797139818,
                "z": -0.6664019480818801,
                "visibility": 0.9999797344207764
            },
            {
                "x": 25.550005178026467,
                "y": 12.057470142997145,
                "z": 0.663744217556185,
                "visibility": 0.9999792575836182
            },
            {
                "x": 25.48861937312425,
                "y": 12.596351971936707,
                "z": -0.8103391563279234,
                "visibility": 0.9898619651794434
            },
            {
                "x": 26.002139544969385,
                "y": 12.805674959034699,
                "z": 2.5074385304747704,
                "visibility": 0.9453256130218506
            },
            {
                "x": 25.44520765713109,
                "y": 14.119843878710286,
                "z": 4.22142672629638,
                "visibility": 0.9564161896705627
            },
            {
                "x": 26.12492758071753,
                "y": 11.820439668718068,
                "z": 8.313405209979324,
                "visibility": 0.8125472664833069
            },
            {
                "x": 25.45692551472807,
                "y": 14.338070753922752,
                "z": 4.698853710039054,
                "visibility": 0.906079113483429
            },
            {
                "x": 26.21326219952554,
                "y": 11.738130291388652,
                "z": 8.899399725355112,
                "visibility": 0.7271711230278015
            },
            {
                "x": 25.31951428258853,
                "y": 14.701564568855984,
                "z": 3.639129331533098,
                "visibility": 0.9648052453994751
            },
            {
                "x": 26.386020009294665,
                "y": 12.061508871907828,
                "z": 8.202637371854646,
                "visibility": 0.8213850855827332
            }
        ],
        "gaze_features": {
            "gaze_vector": [
                0.04206264218692331,
                -0.9991149754318843
            ],
            "gaze_angle_degrees": -87.58927690249449
        },
        "shoulder_width": 0.029029513707419602
    },
    {
        "keypoints": [
            {
                "x": 23.942697898560816,
                "y": 8.857296725290349,
                "z": -10.941927317955788,
                "visibility": 0.999407172203064
            },
            {
                "x": 24.041666504974458,
                "y": 8.594957932496229,
                "z": -11.070348794949687,
                "visibility": 0.9994422793388367
            },
            {
                "x": 24.094352594085358,
                "y": 8.582517639581093,
                "z": -11.07590297389447,
                "visibility": 0.9993001222610474
            },
            {
                "x": 24.1434215946116,
                "y": 8.571457733670929,
                "z": -11.075158395517148,
                "visibility": 0.9995439648628235
            },
            {
                "x": 23.9103042894757,
                "y": 8.594814554189838,
                "z": -10.872121859061904,
                "visibility": 0.9995235204696655
            },
            {
                "x": 23.876130811759538,
                "y": 8.58898746205496,
                "z": -10.87723700374436,
                "visibility": 0.9995457530021667
            },
            {
                "x": 23.839762162731745,
                "y": 8.584616895749827,
                "z": -10.881163591707638,
                "visibility": 0.9997101426124573
            },
            {
                "x": 24.259979258363643,
                "y": 8.582686727101043,
                "z": -10.096497628734173,
                "visibility": 0.9992129802703857
            },
            {
                "x": 23.9031848149515,
                "y": 8.625478724255116,
                "z": -9.233769594050564,
                "visibility": 0.9985948204994202
            },
            {
                "x": 24.060505425618217,
                "y": 9.053149514187492,
                "z": -10.412768418680928,
                "visibility": 0.9990781545639038
            },
            {
                "x": 23.92485174908682,
                "y": 9.08480942187025,
                "z": -10.18533878263714,
                "visibility": 0.9992701411247253
            },
            {
                "x": 24.823726938035247,
                "y": 9.529327657211423,
                "z": -8.681712684837242,
                "visibility": 0.999866247177124
            },
            {
                "x": 23.823763121370416,
                "y": 9.520820873970909,
                "z": -6.233995813148896,
                "visibility": 0.9999161958694458
            },
            {
                "x": 25.030557561122347,
                "y": 11.602945807130192,
                "z": -7.6563916730753805,
                "visibility": 0.9449573159217834
            },
            {
                "x": 23.93936756658894,
                "y": 10.585991166750173,
                "z": -4.148081243029335,
                "visibility": 0.3971668779850006
            },
            {
                "x": 25.076019361222993,
                "y": 13.361755625827389,
                "z": -7.720831816862554,
                "visibility": 0.9108424782752991
            },
            {
                "x": 24.44112044420925,
                "y": 10.79115761266724,
                "z": -4.557148450503611,
                "visibility": 0.6122909188270569
            },
            {
                "x": 25.1116978167483,
                "y": 13.94022479670959,
                "z": -8.647699395297872,
                "visibility": 0.8324445486068726
            },
            {
                "x": 24.62447657768461,
                "y": 10.928585224934254,
                "z": -5.110125947325549,
                "visibility": 0.5345938801765442
            },
            {
                "x": 25.009313840194856,
                "y": 13.900557457818916,
                "z": -8.820361484748338,
                "visibility": 0.8297951221466064
            },
            {
                "x": 24.62393075130442,
                "y": 10.812463628996818,
                "z": -5.696217900028175,
                "visibility": 0.5533998012542725
            },
            {
                "x": 24.992341803981883,
                "y": 13.703403387189294,
                "z": -7.804528161605879,
                "visibility": 0.6753934025764465
            },
            {
                "x": 24.578109022213937,
                "y": 10.779746677110396,
                "z": -4.815565599413983,
                "visibility": 0.4364350438117981
            },
            {
                "x": 25.722408319066073,
                "y": 11.171411713452532,
                "z": -0.7680816661976897,
                "visibility": 0.9999004602432251
            },
            {
                "x": 25.217247981833207,
                "y": 11.18145907187481,
                "z": 0.7668347075390542,
                "visibility": 0.999916672706604
            },
            {
                "x": 25.420683011098625,
                "y": 12.525617839675762,
                "z": 4.746042941869255,
                "visibility": 0.04590420424938202
            },
            {
                "x": 24.750170900409376,
                "y": 12.201384115236872,
                "z": 5.108712929395676,
                "visibility": 0.013439200818538666
            },
            {
                "x": 25.109237642773827,
                "y": 13.214276699874471,
                "z": 11.161998186026088,
                "visibility": 0.06848619133234024
            },
            {
                "x": 24.729585730875375,
                "y": 13.295426843659488,
                "z": 11.527099671865706,
                "visibility": 0.012286242097616196
            },
            {
                "x": 25.234285279895982,
                "y": 13.655277717037508,
                "z": 11.758430186659211,
                "visibility": 0.0399913564324379
            },
            {
                "x": 24.772767321496467,
                "y": 13.378559563336315,
                "z": 12.175591841141141,
                "visibility": 0.010495590977370739
            },
            {
                "x": 25.030306401882186,
                "y": 13.879446238222847,
                "z": 10.619202526589664,
                "visibility": 0.08283013850450516
            },
            {
                "x": 24.830609096741973,
                "y": 13.446585153599148,
                "z": 11.155186233248697,
                "visibility": 0.0240480899810791
            }
        ],
        "gaze_features": {
            "gaze_vector": [
                0.26831728985874337,
                -0.9633305932870913
            ],
            "gaze_angle_degrees": -74.43583969978734
        },
        "shoulder_width": 0.030139404314462246
    },
    {
        "keypoints": [
            {
                "x": 25.758289693996854,
                "y": 9.50997596917345,
                "z": -11.907760082154834,
                "visibility": 0.9969207048416138
            },
            {
                "x": 25.842535863236137,
                "y": 9.309054611222395,
                "z": -12.177137847817963,
                "visibility": 0.996105968952179
            },
            {
                "x": 25.886649988393977,
                "y": 9.280753696677335,
                "z": -12.184922944226411,
                "visibility": 0.9964208602905273
            },
            {
                "x": 25.93110305942502,
                "y": 9.26821909457392,
                "z": -12.183269783693895,
                "visibility": 0.9971364736557007
            },
            {
                "x": 25.75338670337817,
                "y": 9.323113403887705,
                "z": -11.858651301771095,
                "visibility": 0.9948093891143799
            },
            {
                "x": 25.73934283285822,
                "y": 9.3051013085692,
                "z": -11.86663251780429,
                "visibility": 0.9959779381752014
            },
            {
                "x": 25.71693829746589,
                "y": 9.28737699748266,
                "z": -11.871425724067816,
                "visibility": 0.9956911206245422
            },
            {
                "x": 26.075517450495752,
                "y": 9.188810898034244,
                "z": -11.54005710310412,
                "visibility": 0.996612012386322
            },
            {
                "x": 25.8221181049119,
                "y": 9.123736487981535,
                "z": -10.073245387725596,
                "visibility": 0.9767376780509949
            },
            {
                "x": 25.923349939042346,
                "y": 9.550233785622941,
                "z": -11.454260096614796,
                "visibility": 0.993533730506897
            },
            {
                "x": 25.813819260356016,
                "y": 9.564453524284648,
                "z": -11.066882268905328,
                "visibility": 0.9906405210494995
            },
            {
                "x": 26.56483591424032,
                "y": 9.67219354552763,
                "z": -10.00637072742181,
                "visibility": 0.9999165534973145
            },
            {
                "x": 25.674894087043157,
                "y": 9.216119489912783,
                "z": -6.9940910696645355,
                "visibility": 0.9997630715370178
            },
            {
                "x": 26.950773754922434,
                "y": 11.320029003885564,
                "z": -10.83462014222563,
                "visibility": 0.8811176419258118
            },
            {
                "x": 25.139044110592234,
                "y": 9.498004145123657,
                "z": -5.854265660917376,
                "visibility": 0.13788239657878876
            },
            {
                "x": 26.22387981488205,
                "y": 10.700547863757741,
                "z": -12.64609291248211,
                "visibility": 0.6467970013618469
            },
            {
                "x": 24.628704607503824,
                "y": 9.320359202201036,
                "z": -7.287767417313342,
                "visibility": 0.10551764816045761
            },
            {
                "x": 26.032978677541045,
                "y": 10.476633611540116,
                "z": -13.749023849757444,
                "visibility": 0.5211185812950134
            },
            {
                "x": 24.485707820242407,
                "y": 9.0419172990985,
                "z": -8.035922749824634,
                "visibility": 0.10381685942411423
            },
            {
                "x": 26.02249267282222,
                "y": 10.103020397058836,
                "z": -13.926767918359962,
                "visibility": 0.5196764469146729
            },
            {
                "x": 24.475865599509163,
                "y": 9.13784004708293,
                "z": -8.506581603728774,
                "visibility": 0.11194638907909393
            },
            {
                "x": 26.096080166803496,
                "y": 10.219989765207728,
                "z": -12.781476208006735,
                "visibility": 0.4186617434024811
            },
            {
                "x": 24.533207140662185,
                "y": 9.299146306702552,
                "z": -7.586294528072067,
                "visibility": 0.12776818871498108
            },
            {
                "x": 27.374119282290042,
                "y": 12.06515887142487,
                "z": -1.047535403757539,
                "visibility": 0.9999698400497437
            },
            {
                "x": 26.772223890470407,
                "y": 11.770202416877577,
                "z": 1.045574407360227,
                "visibility": 0.9999668598175049
            },
            {
                "x": 27.671728681109055,
                "y": 13.512246708238454,
                "z": 3.2008465452167734,
                "visibility": 0.57536381483078
            },
            {
                "x": 26.223613348000598,
                "y": 12.855950503769478,
                "z": 4.958582538292488,
                "visibility": 0.2230421006679535
            },
            {
                "x": 27.859462060163377,
                "y": 14.572343627254437,
                "z": 9.949731592968288,
                "visibility": 0.8921381235122681
            },
            {
                "x": 26.620139516684013,
                "y": 14.098417356449954,
                "z": 12.194230099461702,
                "visibility": 0.7229191064834595
            },
            {
                "x": 27.867841910651222,
                "y": 14.59288928968177,
                "z": 10.515555895979778,
                "visibility": 0.6648198962211609
            },
            {
                "x": 26.792283517305975,
                "y": 14.213225145256521,
                "z": 12.871713618608544,
                "visibility": 0.6391290426254272
            },
            {
                "x": 27.759890847638133,
                "y": 15.510617217409031,
                "z": 8.892102690208299,
                "visibility": 0.861003577709198
            },
            {
                "x": 26.47850490812057,
                "y": 15.049045417096103,
                "z": 11.743558926335139,
                "visibility": 0.7595710754394531
            }
        ],
        "gaze_features": {
            "gaze_vector": [
                0.40891164814259523,
                -0.9125739772825578
            ],
            "gaze_angle_degrees": -65.86351544216078
        },
        "shoulder_width": 0.027960625186800942
    },
    {
        "keypoints": [
            {
                "x": 25.64924764210515,
                "y": 8.94549680560627,
                "z": -8.851822600075637,
                "visibility": 0.999998927116394
            },
            {
                "x": 25.71493563841754,
                "y": 8.674876822592356,
                "z": -8.900526747777146,
                "visibility": 0.9999984502792358
            },
            {
                "x": 25.76719395788262,
                "y": 8.653870594273917,
                "z": -8.905202514300921,
                "visibility": 0.9999982118606567
            },
            {
                "x": 25.830922845899043,
                "y": 8.63965969405939,
                "z": -8.905326668317528,
                "visibility": 0.9999986886978149
            },
            {
                "x": 25.6348731321484,
                "y": 8.69419013724366,
                "z": -8.61590997761972,
                "visibility": 0.9999985694885254
            },
            {
                "x": 25.61921289161288,
                "y": 8.687491081110252,
                "z": -8.620073871863157,
                "visibility": 0.9999985694885254
            },
            {
                "x": 25.5989442223253,
                "y": 8.681649529413583,
                "z": -8.621871474722264,
                "visibility": 0.9999988079071045
            },
            {
                "x": 26.042289798410515,
                "y": 8.651564801668865,
                "z": -8.103522668544683,
                "visibility": 0.9999986886978149
            },
            {
                "x": 25.73712974711522,
                "y": 8.682799532296231,
                "z": -6.841935837394622,
                "visibility": 0.9999946355819702
            },
            {
                "x": 25.81001446778013,
                "y": 9.120142577324257,
                "z": -8.464699328689152,
                "visibility": 0.999998927116394
            },
            {
                "x": 25.687924774736548,
                "y": 9.136194218657897,
                "z": -8.120338698802607,
                "visibility": 0.9999983310699463
            },
            {
                "x": 26.757549505309875,
                "y": 9.442327511185075,
                "z": -7.099028819438036,
                "visibility": 0.9999986886978149
            },
            {
                "x": 25.767358093701183,
                "y": 9.582044970281611,
                "z": -4.098881203071245,
                "visibility": 0.9999984502792358
            },
            {
                "x": 27.530111551637177,
                "y": 10.223685553943241,
                "z": -6.472449801435233,
                "visibility": 0.9774715304374695
            },
            {
                "x": 25.757002806993942,
                "y": 11.015205287314956,
                "z": -3.269339565151544,
                "visibility": 0.6048213839530945
            },
            {
                "x": 27.945541412733917,
                "y": 11.521701067440878,
                "z": -6.249466557225804,
                "visibility": 0.9579139947891235
            },
            {
                "x": 25.370989030611803,
                "y": 12.336656449676351,
                "z": -4.5110194044988505,
                "visibility": 0.8617000579833984
            },
            {
                "x": 28.123317338684178,
                "y": 11.874401585570153,
                "z": -6.625843667183271,
                "visibility": 0.8950490355491638
            },
            {
                "x": 25.287039872331224,
                "y": 12.761626179150916,
                "z": -4.821109843267233,
                "visibility": 0.8008405566215515
            },
            {
                "x": 28.03305736861026,
                "y": 11.92841068709994,
                "z": -6.920834662796235,
                "visibility": 0.8948793411254883
            },
            {
                "x": 25.218490020720754,
                "y": 12.714203553417445,
                "z": -5.335711407663893,
                "visibility": 0.8101128935813904
            },
            {
                "x": 27.942395476211395,
                "y": 11.844303705916893,
                "z": -6.335148084899134,
                "visibility": 0.8269502520561218
            },
            {
                "x": 25.260458286944946,
                "y": 12.569353693532662,
                "z": -4.773169032337327,
                "visibility": 0.7591096758842468
            },
            {
                "x": 27.309574036339654,
                "y": 11.188329646253155,
                "z": -0.8397045122050185,
                "visibility": 0.9999971389770508
            },
            {
                "x": 26.730319793870795,
                "y": 11.442694922465586,
                "z": 0.8382950221668972,
                "visibility": 0.9999985694885254
            },
            {
                "x": 27.243191619256407,
                "y": 13.621302259029614,
                "z": -1.4901731829543454,
                "visibility": 0.5619634389877319
            },
            {
                "x": 26.3232755896585,
                "y": 13.624099933014023,
                "z": -1.9347279455106294,
                "visibility": 0.9408150315284729
            },
            {
                "x": 27.616461722340627,
                "y": 12.540143830743954,
                "z": 3.649740896083764,
                "visibility": 0.06932536512613297
            },
            {
                "x": 26.991344144414676,
                "y": 15.65356567889883,
                "z": -0.2370469252477466,
                "visibility": 0.9111868739128113
            },
            {
                "x": 27.699901638722576,
                "y": 12.321466521390184,
                "z": 4.09823491828564,
                "visibility": 0.05916741117835045
            },
            {
                "x": 27.203883195015138,
                "y": 16.052700851392128,
                "z": -0.12478656586898682,
                "visibility": 0.7480605840682983
            },
            {
                "x": 27.66040803560908,
                "y": 13.167097415101948,
                "z": 3.3912143560096024,
                "visibility": 0.1425684541463852
            },
            {
                "x": 26.547415675743018,
                "y": 16.30295115846089,
                "z": -1.5164951496660661,
                "visibility": 0.9177971482276917
            }
        ],
        "gaze_features": {
            "gaze_vector": [
                0.2735066890661338,
                -0.9618701009159611
            ],
            "gaze_angle_degrees": -74.1269576662648
        },
        "shoulder_width": 0.028325092798691998
    },
    {
        "keypoints": [
            {
                "x": 20.686289550552438,
                "y": 6.929424786146706,
                "z": -8.040142279294493,
                "visibility": 0.9999685287475586
            },
            {
                "x": 20.76485950909088,
                "y": 6.712480908479123,
                "z": -8.012281104427295,
                "visibility": 0.9999755620956421
            },
            {
                "x": 20.805831923937504,
                "y": 6.699975985615779,
                "z": -8.017103069239624,
                "visibility": 0.9999675750732422
            },
            {
                "x": 20.85005651790991,
                "y": 6.687095423458062,
                "z": -8.016328260672708,
                "visibility": 0.9999834299087524
            },
            {
                "x": 20.688092955307972,
                "y": 6.738851711336096,
                "z": -7.86602800403632,
                "visibility": 0.9999768733978271
            },
            {
                "x": 20.672332912071578,
                "y": 6.741350510982221,
                "z": -7.871264264535731,
                "visibility": 0.9999719858169556
            },
            {
                "x": 20.65508711878496,
                "y": 6.7428396224579,
                "z": -7.874066853007171,
                "visibility": 0.9999785423278809
            },
            {
                "x": 21.00101141215327,
                "y": 6.718105413618357,
                "z": -6.964145369828933,
                "visibility": 0.9999716281890869
            },
            {
                "x": 20.732467132713037,
                "y": 6.783940191649923,
                "z": -6.3292300863461435,
                "visibility": 0.9998747110366821
            },
            {
                "x": 20.767294861831576,
                "y": 7.100618823042585,
                "z": -7.557652513690751,
                "visibility": 0.9999699592590332
            },
            {
                "x": 20.679183497144795,
                "y": 7.121915974356435,
                "z": -7.402778197369192,
                "visibility": 0.9999619722366333
            },
            {
                "x": 21.434468905030453,
                "y": 7.472116841257329,
                "z": -5.961909059434935,
                "visibility": 0.9999858140945435
            },
            {
                "x": 20.535223729269127,
                "y": 7.909561825078133,
                "z": -3.5781924356539343,
                "visibility": 0.9999552965164185
            },
            {
                "x": 22.28849786631074,
                "y": 7.038236649129432,
                "z": -4.5964711490223795,
                "visibility": 0.8989944458007812
            },
            {
                "x": 20.28535721035849,
                "y": 8.519938702754017,
                "z": -1.5256800030043756,
                "visibility": 0.14378702640533447
            },
            {
                "x": 22.805032989258834,
                "y": 7.629734080748538,
                "z": -4.029552040137435,
                "visibility": 0.8495238423347473
            },
            {
                "x": 20.531934574463367,
                "y": 8.008768414828909,
                "z": -0.8648311120625937,
                "visibility": 0.2694894075393677
            },
            {
                "x": 23.098789640309302,
                "y": 7.8130460564024835,
                "z": -4.37962895447475,
                "visibility": 0.6933305859565735
            },
            {
                "x": 20.551375378570796,
                "y": 7.970040591828524,
                "z": -0.9221290249335369,
                "visibility": 0.2135387808084488
            },
            {
                "x": 23.02811567015996,
                "y": 7.942261771884925,
                "z": -4.669880058955919,
                "visibility": 0.7035897374153137
            },
            {
                "x": 20.68890137812942,
                "y": 8.018608987842569,
                "z": -1.3697167949251345,
                "visibility": 0.2173706442117691
            },
            {
                "x": 22.917980245905117,
                "y": 7.9117627183934855,
                "z": -4.108185445581301,
                "visibility": 0.6383887529373169
            },
            {
                "x": 20.698360429354164,
                "y": 8.041096083766782,
                "z": -1.0323045762047274,
                "visibility": 0.20067083835601807
            },
            {
                "x": 22.1744816763704,
                "y": 8.292979457949217,
                "z": -1.1106313566205528,
                "visibility": 0.999749481678009
            },
            {
                "x": 21.980206411601493,
                "y": 8.316930454658213,
                "z": 1.1043207005107254,
                "visibility": 0.9996585845947266
            },
            {
                "x": 21.456474476758522,
                "y": 10.401561307511193,
                "z": -2.0136841870637645,
                "visibility": 0.812008261680603
            },
            {
                "x": 21.6252012273719,
                "y": 9.829697961963067,
                "z": 2.3070956617380274,
                "visibility": 0.045739203691482544
            },
            {
                "x": 22.066887489758027,
                "y": 12.029568563621275,
                "z": -0.3188600914671141,
                "visibility": 0.7848600745201111
            },
            {
                "x": 22.199621777333395,
                "y": 10.632909733601249,
                "z": 5.261727499000318,
                "visibility": 0.11570429801940918
            },
            {
                "x": 22.242328687713773,
                "y": 12.306931542737457,
                "z": -0.17928550005341035,
                "visibility": 0.605767011642456
            },
            {
                "x": 22.11641473238254,
                "y": 10.626171756280709,
                "z": 5.548466754239465,
                "visibility": 0.10436301678419113
            },
            {
                "x": 21.91324681657772,
                "y": 13.102580947462751,
                "z": -1.6011473658496969,
                "visibility": 0.8357998728752136
            },
            {
                "x": 22.19185016168606,
                "y": 11.305090620012368,
                "z": 4.684285447734754,
                "visibility": 0.17826421558856964
            }
        ],
        "gaze_features": {
            "gaze_vector": [
                0.41004236586165316,
                -0.9120664768527448
            ],
            "gaze_angle_degrees": -65.7925038138886
        },
        "shoulder_width": 0.035463909944622035
    },
    {
        "keypoints": [
            {
                "x": 19.17407072792391,
                "y": 6.267993828468556,
                "z": -7.957431920987336,
                "visibility": 0.9999997615814209
            },
            {
                "x": 19.20792045928588,
                "y": 6.019625558712975,
                "z": -7.942842156065611,
                "visibility": 0.9999998807907104
            },
            {
                "x": 19.255571589865273,
                "y": 6.0019346323086,
                "z": -7.946564011327155,
                "visibility": 0.9999998807907104
            },
            {
                "x": 19.301818275785116,
                "y": 5.994718586418167,
                "z": -7.945617203344728,
                "visibility": 0.9999998807907104
            },
            {
                "x": 19.150938155316723,
                "y": 6.022311386068485,
                "z": -7.743185657188179,
                "visibility": 0.9999998807907104
            },
            {
                "x": 19.140136391461976,
                "y": 6.010598963683118,
                "z": -7.747077491786942,
                "visibility": 0.9999998807907104
            },
            {
                "x": 19.126227313026398,
                "y": 5.999801045514733,
                "z": -7.749161084658097,
                "visibility": 0.9999997615814209
            },
            {
                "x": 19.469517890128163,
                "y": 5.986009645081845,
                "z": -6.862540401215439,
                "visibility": 0.9999998807907104
            },
            {
                "x": 19.20757127096417,
                "y": 6.00295873858691,
                "z": -5.933205294776815,
                "visibility": 0.9999986886978149
            },
            {
                "x": 19.286169408839182,
                "y": 6.4143864175206495,
                "z": -7.449372911687956,
                "visibility": 0.9999997615814209
            },
            {
                "x": 19.187696763843217,
                "y": 6.417142236367955,
                "z": -7.203184376962591,
                "visibility": 0.9999995231628418
            },
            {
                "x": 20.018478850440903,
                "y": 6.4720455622895905,
                "z": -5.341902173907992,
                "visibility": 0.9999988079071045
            },
            {
                "x": 19.024068962220696,
                "y": 6.577634265330565,
                "z": -3.2108006548525867,
                "visibility": 0.9999903440475464
            },
            {
                "x": 20.66480182152814,
                "y": 6.607299889930225,
                "z": -3.611077573894189,
                "visibility": 0.994517982006073
            },
            {
                "x": 18.81109023664659,
                "y": 7.440287862225389,
                "z": -1.3172157439174625,
                "visibility": 0.6846648454666138
            },
            {
                "x": 20.942158875083596,
                "y": 7.6843774213341485,
                "z": -2.3292741598498994,
                "visibility": 0.9889660477638245
            },
            {
                "x": 18.579604530022007,
                "y": 8.349352740416366,
                "z": -0.8559247994665089,
                "visibility": 0.7610730528831482
            },
            {
                "x": 21.138824199108342,
                "y": 7.898704444546916,
                "z": -2.389802378929519,
                "visibility": 0.9596144556999207
            },
            {
                "x": 18.52833537771285,
                "y": 8.437221289836613,
                "z": -0.8254372555490428,
                "visibility": 0.6151466965675354
            },
            {
                "x": 21.094158859420723,
                "y": 7.9909724591657625,
                "z": -2.7176027236478,
                "visibility": 0.9632534384727478
            },
            {
                "x": 18.553133901652238,
                "y": 8.522057130991458,
                "z": -1.1997763660663914,
                "visibility": 0.6316574215888977
            },
            {
                "x": 20.98760411996551,
                "y": 7.921404762006971,
                "z": -2.3971762902451292,
                "visibility": 0.9421923756599426
            },
            {
                "x": 18.590766250120275,
                "y": 8.474742113400138,
                "z": -0.9939965730784066,
                "visibility": 0.5659673810005188
            },
            {
                "x": 20.199061514098034,
                "y": 8.132386038084439,
                "z": -0.8915143193388301,
                "visibility": 0.9999703168869019
            },
            {
                "x": 19.755167781755528,
                "y": 8.352981530067941,
                "z": 0.8885662161734038,
                "visibility": 0.999924898147583
            },
            {
                "x": 19.62699105529628,
                "y": 9.530441474315404,
                "z": -3.7949971396079873,
                "visibility": 0.9825515151023865
            },
            {
                "x": 20.09105310519783,
                "y": 9.678972649553636,
                "z": 2.1150405868157387,
                "visibility": 0.611834704875946
            },
            {
                "x": 19.65470307122383,
                "y": 11.57551441259066,
                "z": -2.4696057549105106,
                "visibility": 0.9939603805541992
            },
            {
                "x": 20.79129413736065,
                "y": 10.488881888850683,
                "z": 5.8854249491356425,
                "visibility": 0.8511379361152649
            },
            {
                "x": 19.728841751192988,
                "y": 11.880053546492928,
                "z": -2.4291854761140432,
                "visibility": 0.9619623422622681
            },
            {
                "x": 20.94322951416689,
                "y": 10.46340037101333,
                "z": 6.205843306596952,
                "visibility": 0.7821812033653259
            },
            {
                "x": 19.426243150629194,
                "y": 12.140816463394568,
                "z": -4.4842383550684,
                "visibility": 0.997869610786438
            },
            {
                "x": 20.896147545169136,
                "y": 11.433426300284017,
                "z": 4.966970827690831,
                "visibility": 0.936412513256073
            }
        ],
        "gaze_features": {
            "gaze_vector": [
                0.15947991374891304,
                -0.987201173576409
            ],
            "gaze_angle_degrees": -80.82329014543446
        },
        "shoulder_width": 0.038747728726622306
    },
    {
        "keypoints": [
            {
                "x": 19.318288358717204,
                "y": 6.102988589588598,
                "z": -8.711495877498328,
                "visibility": 0.9999908208847046
            },
            {
                "x": 19.37994730609046,
                "y": 5.898887625042247,
                "z": -8.714213485670689,
                "visibility": 0.9999951124191284
            },
            {
                "x": 19.424400104290015,
                "y": 5.890799998576151,
                "z": -8.71846056341564,
                "visibility": 0.999992847442627
            },
            {
                "x": 19.47860653091739,
                "y": 5.8830072974112895,
                "z": -8.717507137799426,
                "visibility": 0.999996542930603
            },
            {
                "x": 19.30416415976551,
                "y": 5.8993286706812835,
                "z": -8.460284718897734,
                "visibility": 0.9999947547912598
            },
            {
                "x": 19.29150346529952,
                "y": 5.891678254674755,
                "z": -8.464169755700729,
                "visibility": 0.999993085861206
            },
            {
                "x": 19.277721364356537,
                "y": 5.881937665857138,
                "z": -8.466140270912357,
                "visibility": 0.9999954700469971
            },
            {
                "x": 19.64522667002249,
                "y": 5.873592698848612,
                "z": -7.524299197805383,
                "visibility": 0.9999923706054688
            },
            {
                "x": 19.383250162649926,
                "y": 5.874977965673136,
                "z": -6.3256430018564185,
                "visibility": 0.9998931884765625
            },
            {
                "x": 19.426664394249038,
                "y": 6.27265117656716,
                "z": -8.142367516741517,
                "visibility": 0.9999908208847046
            },
            {
                "x": 19.35220515187709,
                "y": 6.285728371523578,
                "z": -7.82071484978163,
                "visibility": 0.9999815225601196
            },
            {
                "x": 20.189539885537346,
                "y": 6.504662276187661,
                "z": -6.08977639631484,
                "visibility": 0.9999959468841553
            },
            {
                "x": 19.192227543613832,
                "y": 6.577929544780367,
                "z": -3.5703645461879856,
                "visibility": 0.999976396560669
            },
            {
                "x": 20.640188813966855,
                "y": 7.571073046620115,
                "z": -5.174892799701697,
                "visibility": 0.9532490968704224
            },
            {
                "x": 19.110015102425564,
                "y": 7.753272451767787,
                "z": -2.768720376192437,
                "visibility": 0.629168689250946
            },
            {
                "x": 20.40333733433741,
                "y": 8.745448721345229,
                "z": -5.572438299119374,
                "visibility": 0.9385640621185303
            },
            {
                "x": 18.858166536997075,
                "y": 9.112700138130275,
                "z": -4.644416144678294,
                "visibility": 0.8615636825561523
            },
            {
                "x": 20.396811392951452,
                "y": 9.179352489173322,
                "z": -6.074360508917685,
                "visibility": 0.8828732967376709
            },
            {
                "x": 18.690840724869517,
                "y": 9.399614516487826,
                "z": -5.0771083793118486,
                "visibility": 0.774682343006134
            },
            {
                "x": 20.274693142343125,
                "y": 9.128994281626033,
                "z": -6.337250172522029,
                "visibility": 0.8932030200958252
            },
            {
                "x": 18.697015363816035,
                "y": 9.425136868824024,
                "z": -5.6218756800759415,
                "visibility": 0.7979588508605957
            },
            {
                "x": 20.256767513500876,
                "y": 9.015104025052398,
                "z": -5.651131196108127,
                "visibility": 0.7915126085281372
            },
            {
                "x": 18.79194219198287,
                "y": 9.340815078927319,
                "z": -4.914864179981889,
                "visibility": 0.7016435861587524
            },
            {
                "x": 20.357804549599134,
                "y": 8.342438858218859,
                "z": -0.9670171087370419,
                "visibility": 0.9999558925628662
            },
            {
                "x": 19.846799100744345,
                "y": 8.707847087750677,
                "z": 0.9629894032577674,
                "visibility": 0.999864935874939
            },
            {
                "x": 20.0270648084033,
                "y": 10.27209866998959,
                "z": -4.840342424184582,
                "visibility": 0.7171754837036133
            },
            {
                "x": 20.022821565837816,
                "y": 10.35065848625074,
                "z": 2.9147935412876222,
                "visibility": 0.045627400279045105
            },
            {
                "x": 19.813891726820934,
                "y": 12.28658421423937,
                "z": -2.6591642559377204,
                "visibility": 0.7520310282707214
            },
            {
                "x": 20.806540490509065,
                "y": 9.181146586129334,
                "z": 8.716174029415694,
                "visibility": 0.009813273325562477
            },
            {
                "x": 19.84572831863635,
                "y": 12.521227397530055,
                "z": -2.5179512220257485,
                "visibility": 0.39776402711868286
            },
            {
                "x": 20.85043335250602,
                "y": 8.875640024737669,
                "z": 9.284266891715635,
                "visibility": 0.02811896800994873
            },
            {
                "x": 19.635532870394403,
                "y": 13.016978036525426,
                "z": -4.641810140228506,
                "visibility": 0.8758313655853271
            },
            {
                "x": 21.06342387954562,
                "y": 9.637028233427557,
                "z": 8.457704410150395,
                "visibility": 0.03700549900531769
            }
        ],
        "gaze_features": {
            "gaze_vector": [
                0.3159438697847234,
                -0.948777882934385
            ],
            "gaze_angle_degrees": -71.58219625067576
        },
        "shoulder_width": 0.03885388235635755
    },
    {
        "keypoints": [
            {
                "x": 19.33875227800981,
                "y": 6.0849373848349035,
                "z": -7.1966029679528445,
                "visibility": 0.9998480081558228
            },
            {
                "x": 19.415654410178128,
                "y": 5.84700249668864,
                "z": -7.262716055658175,
                "visibility": 0.9999254941940308
            },
            {
                "x": 19.455459839168807,
                "y": 5.841794466866396,
                "z": -7.266927421129347,
                "visibility": 0.9999016523361206
            },
            {
                "x": 19.49316340698966,
                "y": 5.840037693085001,
                "z": -7.265816874118528,
                "visibility": 0.9999423027038574
            },
            {
                "x": 19.346552858045886,
                "y": 5.847413697164773,
                "z": -6.961838832920403,
                "visibility": 0.9999271631240845
            },
            {
                "x": 19.33179702832058,
                "y": 5.842351268998111,
                "z": -6.965762052333021,
                "visibility": 0.9999252557754517
            },
            {
                "x": 19.317113044031622,
                "y": 5.8375678151321715,
                "z": -6.96852580869305,
                "visibility": 0.9999552965164185
            },
            {
                "x": 19.675549925983272,
                "y": 5.840813088778377,
                "z": -6.526874332245236,
                "visibility": 0.9999165534973145
            },
            {
                "x": 19.468434819248408,
                "y": 5.834735270588403,
                "z": -5.169288699318588,
                "visibility": 0.9996145963668823
            },
            {
                "x": 19.44200487042933,
                "y": 6.267099960074787,
                "z": -6.8287856706785615,
                "visibility": 0.9999215602874756
            },
            {
                "x": 19.360203490952443,
                "y": 6.258916076992651,
                "z": -6.459720250025979,
                "visibility": 0.9998748302459717
            },
            {
                "x": 20.23708009886048,
                "y": 6.718090961091564,
                "z": -5.617158627576465,
                "visibility": 0.999980092048645
            },
            {
                "x": 19.24723036385736,
                "y": 6.575973044859141,
                "z": -2.958672455612115,
                "visibility": 0.9999790191650391
            },
            {
                "x": 20.38864645428612,
                "y": 8.2920624371383,
                "z": -5.365468013465154,
                "visibility": 0.8119593858718872
            },
            {
                "x": 19.18889951267244,
                "y": 7.529345934651433,
                "z": -2.6848444664253672,
                "visibility": 0.4722045361995697
            },
            {
                "x": 19.689000308843834,
                "y": 8.95715322063555,
                "z": -5.968148806481725,
                "visibility": 0.7539483308792114
            },
            {
                "x": 19.201684943090182,
                "y": 8.855286327961808,
                "z": -5.424106882850595,
                "visibility": 0.7957919239997864
            },
            {
                "x": 19.543708964401556,
                "y": 9.214096194731962,
                "z": -6.537223132332291,
                "visibility": 0.7075408697128296
            },
            {
                "x": 19.163707751160675,
                "y": 9.208797975957703,
                "z": -6.063997115234825,
                "visibility": 0.7659297585487366
            },
            {
                "x": 19.474335316786966,
                "y": 9.14470191066225,
                "z": -6.698274613982475,
                "visibility": 0.7145926356315613
            },
            {
                "x": 19.269795945376572,
                "y": 9.15372386311628,
                "z": -6.50665366347839,
                "visibility": 0.7850222587585449
            },
            {
                "x": 19.531865167787892,
                "y": 9.034835716532738,
                "z": -6.005789318467485,
                "visibility": 0.5398187637329102
            },
            {
                "x": 19.32588735902419,
                "y": 8.994564056518936,
                "z": -5.684856136447266,
                "visibility": 0.6982303857803345
            },
            {
                "x": 20.299185128393248,
                "y": 8.633045463935746,
                "z": -0.7679809481736924,
                "visibility": 0.9999747276306152
            },
            {
                "x": 19.778851434444565,
                "y": 8.729076061375757,
                "z": 0.7661763092811116,
                "visibility": 0.9999673366546631
            },
            {
                "x": 20.182381263777017,
                "y": 10.695324384208291,
                "z": -0.7659416173736721,
                "visibility": 0.5658055543899536
            },
            {
                "x": 19.88895380133825,
                "y": 10.539317369365682,
                "z": 1.1857043115989525,
                "visibility": 0.23291000723838806
            },
            {
                "x": 20.17071937369369,
                "y": 12.561398768000233,
                "z": 2.1636902823073005,
                "visibility": 0.7131853699684143
            },
            {
                "x": 20.580048811228544,
                "y": 9.30911942743676,
                "z": 5.655397978917337,
                "visibility": 0.06801987439393997
            },
            {
                "x": 20.14902510916851,
                "y": 12.772709189630064,
                "z": 2.3878308466743055,
                "visibility": 0.3394915759563446
            },
            {
                "x": 20.678292095245514,
                "y": 9.186634423156788,
                "z": 6.102284236147738,
                "visibility": 0.0881090983748436
            },
            {
                "x": 20.012642598833665,
                "y": 13.152751675781188,
                "z": 0.7964888733765734,
                "visibility": 0.7303152084350586
            },
            {
                "x": 20.86280034755092,
                "y": 9.815563258462104,
                "z": 5.355128767292508,
                "visibility": 0.12398572266101837
            }
        ],
        "gaze_features": {
            "gaze_vector": [
                0.37274667009670387,
                -0.9279331441067395
            ],
            "gaze_angle_degrees": -68.11488840949504
        },
        "shoulder_width": 0.038992292993869616
    },
    {
        "keypoints": [
            {
                "x": 19.066985608408814,
                "y": 6.00512084805332,
                "z": -6.948501890541055,
                "visibility": 0.9998610019683838
            },
            {
                "x": 19.143449637343963,
                "y": 5.7742701252264625,
                "z": -7.003575103236674,
                "visibility": 0.9999312162399292
            },
            {
                "x": 19.183138403777118,
                "y": 5.768505668017607,
                "z": -7.0077253014127985,
                "visibility": 0.9999104738235474
            },
            {
                "x": 19.22075320155571,
                "y": 5.765892105774135,
                "z": -7.006665708415589,
                "visibility": 0.9999469518661499
            },
            {
                "x": 19.07457157079139,
                "y": 5.773045488938792,
                "z": -6.70938882928966,
                "visibility": 0.999931812286377
            },
            {
                "x": 19.059960341040405,
                "y": 5.76708169862342,
                "z": -6.713168245278994,
                "visibility": 0.9999300241470337
            },
            {
                "x": 19.045867603453058,
                "y": 5.7609634157302185,
                "z": -6.715903140717736,
                "visibility": 0.9999572038650513
            },
            {
                "x": 19.401327141011794,
                "y": 5.762854254158381,
                "z": -6.2568065906506884,
                "visibility": 0.999927282333374
            },
            {
                "x": 19.19620018601583,
                "y": 5.756361797777901,
                "z": -4.929577434211355,
                "visibility": 0.9996353387832642
            },
            {
                "x": 19.168423174144472,
                "y": 6.184203745727772,
                "z": -6.580565381672368,
                "visibility": 0.9999293088912964
            },
            {
                "x": 19.089047148522823,
                "y": 6.175836276988076,
                "z": -6.219925067400039,
                "visibility": 0.9998838901519775
            },
            {
                "x": 19.960157693535557,
                "y": 6.644134932526263,
                "z": -5.392668936254366,
                "visibility": 0.9999819993972778
            },
            {
                "x": 18.971424789609312,
                "y": 6.494444436189397,
                "z": -2.7816398058425658,
                "visibility": 0.9999799728393555
            },
            {
                "x": 20.103698631652488,
                "y": 8.180882401283565,
                "z": -5.180323786573289,
                "visibility": 0.8339902758598328
            },
            {
                "x": 18.921143107693393,
                "y": 7.434907829823154,
                "z": -2.6178326444093494,
                "visibility": 0.4526126980781555
            },
            {
                "x": 19.411894433335313,
                "y": 8.824121669354552,
                "z": -5.812034140226565,
                "visibility": 0.7826467156410217
            },
            {
                "x": 18.936477814882018,
                "y": 8.720401381578679,
                "z": -5.434208599132148,
                "visibility": 0.7902082800865173
            },
            {
                "x": 19.265385730479398,
                "y": 9.078328278648694,
                "z": -6.381370188042713,
                "visibility": 0.7365937829017639
            },
            {
                "x": 18.906316341955776,
                "y": 9.067933565838949,
                "z": -6.085850379381218,
                "visibility": 0.7656465172767639
            },
            {
                "x": 19.19897050170412,
                "y": 8.993976838398616,
                "z": -6.535140795678931,
                "visibility": 0.7430656552314758
            },
            {
                "x": 19.005922605427408,
                "y": 9.013000526896873,
                "z": -6.50774059497301,
                "visibility": 0.784027636051178
            },
            {
                "x": 19.257540522015,
                "y": 8.884808614792853,
                "z": -5.848384359733947,
                "visibility": 0.5731480121612549
            },
            {
                "x": 19.058442545666026,
                "y": 8.855357054102292,
                "z": -5.689409613091879,
                "visibility": 0.6957554817199707
            },
            {
                "x": 20.01404319743772,
                "y": 8.53058426423442,
                "z": -0.7588924589353193,
                "visibility": 0.999971866607666
            },
            {
                "x": 19.508128990498612,
                "y": 8.613834662259093,
                "z": 0.7571510261342519,
                "visibility": 0.999962329864502
            },
            {
                "x": 19.913883775175226,
                "y": 10.554547816279511,
                "z": -0.7107151731755725,
                "visibility": 0.6272560954093933
            },
            {
                "x": 19.619680167914602,
                "y": 10.388154788223483,
                "z": 1.3817489277357164,
                "visibility": 0.23005267977714539
            },
            {
                "x": 19.885369720664272,
                "y": 12.395305779689103,
                "z": 2.2014470747278443,
                "visibility": 0.7288264632225037
            },
            {
                "x": 20.287335292261247,
                "y": 9.184352389890051,
                "z": 5.914820689934486,
                "visibility": 0.06587138026952744
            },
            {
                "x": 19.858450331005447,
                "y": 12.59306456915611,
                "z": 2.426253181244343,
                "visibility": 0.3588736355304718
            },
            {
                "x": 20.381331591101855,
                "y": 9.060578211889617,
                "z": 6.368777158893807,
                "visibility": 0.08894655108451843
            },
            {
                "x": 19.720673096475043,
                "y": 12.985304644573159,
                "z": 0.8616588963472854,
                "visibility": 0.7439917325973511
            },
            {
                "x": 20.538749730819504,
                "y": 9.672114849367723,
                "z": 5.665344944822406,
                "visibility": 0.11900190263986588
            }
        ],
        "gaze_features": {
            "gaze_vector": [
                0.37834502114352003,
                -0.925664650386904
            ],
            "gaze_angle_degrees": -67.76879292659655
        },
        "shoulder_width": 0.03954543432003643
    }
]